harvest/__init__.py
harvest/cli.py
harvest/constants.py
harvest/core.py
harvest/httputil.py
harvest/paths.py
harvest/server.py
harvest/ui.py
harvest/watch.py
harvest_code-1.8.0.dist-info/licenses/LICENSE
harvest_code-1.8.0.dist-info/METADATA
harvest_code-1.8.0.dist-info/WHEEL
harvest_code-1.8.0.dist-info/entry_points.txt
harvest_code-1.8.0.dist-info/top_level.txt
harvest_code-1.8.0.dist-info/RECORD
