Metadata-Version: 2.4
Name: harvest-code
Version: 1.8.0
Summary: Harvest codebases into portable JSON + chunks for RAG and tooling
Author-email: veyorokon <veyorokon@users.noreply.github.com>
License-Expression: MIT
Classifier: Programming Language :: Python :: 3
Classifier: Environment :: Console
Requires-Python: >=3.9
License-File: LICENSE
Provides-Extra: dev
Requires-Dist: pytest>=8.3; extra == "dev"
Requires-Dist: pytest-timeout>=2.3; extra == "dev"
Requires-Dist: requests>=2.25; extra == "dev"
Dynamic: license-file
